Romanize-1.0.2.dist-info/DESCRIPTION.rst
Romanize-1.0.2.dist-info/METADATA
Romanize-1.0.2.dist-info/RECORD
Romanize-1.0.2.dist-info/WHEEL
Romanize-1.0.2.dist-info/metadata.json
Romanize-1.0.2.dist-info/top_level.txt
romanize/__init__.py
romanize/__main__.py
