Metadata-Version: 2.0
Name: Romanize
Version: 1.0.2
Summary: Transcribe Greek text to Latin alphabet using the ISO 843:1997 standard (also known as ELOT 743:1987)
Home-page: https://github.com/gschizas/RomanizePython
Author: George Schizas
Author-email: gschizas@gmail.com
License: Apache Software License
Platform: any
Classifier: Programming Language :: Python
Classifier: Development Status :: 5 - Production/Stable
Classifier: Natural Language :: English
Classifier: Natural Language :: Greek
Classifier: Intended Audience :: Developers
Classifier: License :: OSI Approved :: Apache Software License
Classifier: Operating System :: OS Independent
Classifier: Topic :: Software Development :: Libraries :: Python Modules
Classifier: Topic :: Text Processing
Requires: colorama
